oarepo/__init__.py
oarepo/react-dependencies.json
oarepo/version.py
oarepo/webpack.py
oarepo/assets/semantic-ui/.gitkeep
oarepo/config/__init__.py
oarepo/config/base.py
oarepo/config/communities.py
oarepo/config/cron.py
oarepo/config/generic_parameters.py
oarepo/config/i18n.py
oarepo/config/models.py
oarepo/config/vocabulary.py
oarepo/config/workflows.py
oarepo-12.2.12.dist-info/licenses/LICENSE
oarepo-12.2.12.dist-info/METADATA
oarepo-12.2.12.dist-info/WHEEL
oarepo-12.2.12.dist-info/entry_points.txt
oarepo-12.2.12.dist-info/top_level.txt
oarepo-12.2.12.dist-info/RECORD
